topsis_Prince_101916056/__init__.py
topsis_Prince_101916056-0.0.1.dist-info/METADATA
topsis_Prince_101916056-0.0.1.dist-info/WHEEL
topsis_Prince_101916056-0.0.1.dist-info/top_level.txt
topsis_Prince_101916056-0.0.1.dist-info/RECORD
