Metadata-Version: 2.1
Name: topsis-Prince-101916056
Version: 0.0.1
Summary: A small package to work with topsis
Home-page: https://github.com/Prince-hash-lab/topsis_Prince_101916056
Author: Prince Saini
Author-email: pprince_be19@thapar.edu
License: UNKNOWN
Platform: UNKNOWN
Classifier: Programming Language :: Python :: 3
Classifier: License :: OSI Approved :: MIT License
Classifier: Operating System :: OS Independent
